{
    "hackage-nix": {
        "branch": "master",
        "description": "Automatically generated Nix expressions for Hackage",
        "homepage": "",
        "owner": "input-output-hk",
        "repo": "hackage.nix",
        "rev": "93e877fa2744aa44d2eed632dbbf051cf5a362d0",
        "sha256": "1cly319aq0pa199sb6jvvpa0q3w7nxq11c3qc9lv0ms5vdrzjgig",
        "type": "tarball",
        "url": "https://github.com/input-output-hk/hackage.nix/archive/93e877fa2744aa44d2eed632dbbf051cf5a362d0.tar.gz",
        "url_template": "https://github.com/<owner>/<repo>/archive/<rev>.tar.gz"
    },
    "haskell-nix": {
        "branch": "master",
        "description": "Alternative Haskell Infrastructure for Nixpkgs",
        "homepage": "https://input-output-hk.github.io/haskell.nix",
        "owner": "input-output-hk",
        "repo": "haskell.nix",
        "rev": "1cf91bfad530c2dbe1e8d44d6808943f77f321b5",
        "sha256": "0gxz9kna28s7rypnf8hycv7wi0qic5z9m57glsa3iv7f1zark7fp",
        "type": "tarball",
        "url": "https://github.com/input-output-hk/haskell.nix/archive/1cf91bfad530c2dbe1e8d44d6808943f77f321b5.tar.gz",
        "url_template": "https://github.com/<owner>/<repo>/archive/<rev>.tar.gz"
    },
    "iohk-nix": {
        "branch": "master",
        "description": "nix scripts shared across projects",
        "homepage": null,
        "owner": "input-output-hk",
        "repo": "iohk-nix",
        "rev": "65d5b5eabf5252c7ece10efdc507f0a5c9b2aa8a",
        "sha256": "1b2n1c3cygrczhgffq6px42hln0344l88cf0hgq78l7m5w7lysal",
        "type": "tarball",
        "url": "https://github.com/input-output-hk/iohk-nix/archive/65d5b5eabf5252c7ece10efdc507f0a5c9b2aa8a.tar.gz",
        "url_template": "https://github.com/<owner>/<repo>/archive/<rev>.tar.gz"
    },
    "jupyterWith": {
        "branch": "master",
        "description": "declarative and reproducible Jupyter environments - powered by Nix",
        "homepage": "",
        "owner": "tweag",
        "repo": "jupyterWith",
        "rev": "35eb565c6d00f3c61ef5e74e7e41870cfa3926f7",
        "sha256": "15zpprs0blvlvbqapkyn92x6dpfa6va2xz25v24z67lqs96ii4jm",
        "type": "tarball",
        "url": "https://github.com/tweag/jupyterWith/archive/35eb565c6d00f3c61ef5e74e7e41870cfa3926f7.tar.gz",
        "url_template": "https://github.com/<owner>/<repo>/archive/<rev>.tar.gz"
    },
    "niv": {
        "branch": "master",
        "description": "Easy dependency management for Nix projects",
        "homepage": "https://github.com/nmattia/niv",
        "owner": "nmattia",
        "repo": "niv",
        "rev": "ba57d5a29b4e0f2085917010380ef3ddc3cf380f",
        "sha256": "1kpsvc53x821cmjg1khvp1nz7906gczq8mp83664cr15h94sh8i4",
        "type": "tarball",
        "url": "https://github.com/nmattia/niv/archive/ba57d5a29b4e0f2085917010380ef3ddc3cf380f.tar.gz",
        "url_template": "https://github.com/<owner>/<repo>/archive/<rev>.tar.gz"
    },
    "nixpkgs-2003": {
        "branch": "nixpkgs-20.03-darwin",
        "description": "Nix Packages collection",
        "homepage": null,
        "owner": "NixOS",
        "repo": "nixpkgs",
        "rev": "929768261a3ede470eafb58d5b819e1a848aa8bf",
        "sha256": "0zi54vbfi6i6i5hdd4v0l144y1c8rg6hq6818jjbbcnm182ygyfa",
        "type": "tarball",
        "url": "https://github.com/NixOS/nixpkgs/archive/929768261a3ede470eafb58d5b819e1a848aa8bf.tar.gz",
        "url_template": "https://github.com/<owner>/<repo>/archive/<rev>.tar.gz"
    },
    "nixpkgs-2009": {
        "branch": "nixpkgs-20.09-darwin",
        "description": "Nix Packages collection",
        "homepage": null,
        "owner": "NixOS",
        "repo": "nixpkgs",
        "rev": "5adafbe99cf5e766775240414f00d0b0b814f7e6",
        "sha256": "11gqbkx2132kd30ckkhaaxyabl50ladid80v5iwn64nbl5vzxzcv",
        "type": "tarball",
        "url": "https://github.com/NixOS/nixpkgs/archive/5adafbe99cf5e766775240414f00d0b0b814f7e6.tar.gz",
        "url_template": "https://github.com/<owner>/<repo>/archive/<rev>.tar.gz"
    },
    "nixpkgs-staging-next": {
        "branch": "staging-next",
        "description": "Nix Packages collection",
        "homepage": null,
        "owner": "NixOS",
        "repo": "nixpkgs",
        "rev": "0984deb2b80e309ed7adeecaf1618bef02bc5db9",
        "sha256": "1hbf19xb2rs7hzysrnv1sffxs0v82kxfmxr3bsfsrxqr8bzqh9iv",
        "type": "tarball",
        "url": "https://github.com/NixOS/nixpkgs/archive/0984deb2b80e309ed7adeecaf1618bef02bc5db9.tar.gz",
        "url_template": "https://github.com/<owner>/<repo>/archive/<rev>.tar.gz"
    },
    "pytorch-world": {
        "branch": "unstable",
        "description": "nix scripts for pytorch-related libraries",
        "homepage": "https://pytorch.org/",
        "owner": "stites",
        "repo": "pytorch-world",
        "rev": "e08419a2f2b9ca177903c9595858b0dc386fc4dd",
        "sha256": "0zb0h19aqi31gl4nqhf161wx27v8brf9y2w2psaqqxwbk02f9wp8",
        "type": "tarball",
        "url": "https://github.com/stites/pytorch-world/archive/e08419a2f2b9ca177903c9595858b0dc386fc4dd.tar.gz",
        "url_template": "https://github.com/<owner>/<repo>/archive/<rev>.tar.gz"
    },
    "stackage-nix": {
        "branch": "master",
        "description": "Automatically generated Nix expressions of Stackage snapshots",
        "homepage": "",
        "owner": "input-output-hk",
        "repo": "stackage.nix",
        "rev": "9d96e7979e52a380a66728a300821cb0c59d71a1",
        "sha256": "0k08x7iqh7bnn5fc9q2wqwaj23ybqbaj0ziqgpaz5yajz5i8vk8r",
        "type": "tarball",
        "url": "https://github.com/input-output-hk/stackage.nix/archive/9d96e7979e52a380a66728a300821cb0c59d71a1.tar.gz",
        "url_template": "https://github.com/<owner>/<repo>/archive/<rev>.tar.gz"
    }
}
